{
    "name": "Gvcci",
    "comment": "Gvcci generated theme.",
    "foreground-color": "#1f3131",
    "background-color": "#9bbcc4",
    "use-theme-colors": false,
    "use-highlight-color": false,
    "highlight-foreground-color": "#9bbcc4",
    "highlight-background-color": "#568f84",
    "use-cursor-color": false,
    "cursor-foreground-color": "#3f6960",
    "cursor-background-color": "#3f6960",
    "use-badge-color": true,
    "badge-color": "#1f3131",
    "palette": [
        "#263b40",
        "#725f27",
        "#45434c",
        "#60614d",
        "#37433d",
        "#5b6539",
        "#486564",
        "#d0dce1",
        "#395960",
        "#a08536",
        "#63606c",
        "#828367",
        "#53655c",
        "#7f8c4f",
        "#628988",
        "#f6f8f9"
    ]
}